[
	
	{
		"name" : "A Killer Paradox",
		"language":"Hindi",
		"rating" : "7.1/10",
		"image_url" : "https://i.ibb.co/395F2KDk/p26507881-b-h9-ab.jpg",
		"ep_01" : "https://kmdl.eu.org/0:/A%20Killer%20Paradox%20%7C%202024%20%7C%207.3%20%F0%9F%8C%90%F0%9F%94%9E/Multi%20Audio%20%7C%20Korean%20%7C%20English%20Dubbed%20%7C%20Hindi%20Dubbed%20%7C%20720p%20%7C%20H.265%20%7C%20WEB-DL/Episode%2001.mkv",
		"ep_02" : "https://kmdl.eu.org/0:/A%20Killer%20Paradox%20%7C%202024%20%7C%207.3%20%F0%9F%8C%90%F0%9F%94%9E/Multi%20Audio%20%7C%20Korean%20%7C%20English%20Dubbed%20%7C%20Hindi%20Dubbed%20%7C%20720p%20%7C%20H.265%20%7C%20WEB-DL/Episode%2002.mkv",
		"ep_03" : "https://kmdl.eu.org/0:/A%20Killer%20Paradox%20%7C%202024%20%7C%207.3%20%F0%9F%8C%90%F0%9F%94%9E/Multi%20Audio%20%7C%20Korean%20%7C%20English%20Dubbed%20%7C%20Hindi%20Dubbed%20%7C%20720p%20%7C%20H.265%20%7C%20WEB-DL/Episode%2003.mkv",
		"ep_04" : "https://kmdl.eu.org/0:/A%20Killer%20Paradox%20%7C%202024%20%7C%207.3%20%F0%9F%8C%90%F0%9F%94%9E/Multi%20Audio%20%7C%20Korean%20%7C%20English%20Dubbed%20%7C%20Hindi%20Dubbed%20%7C%20720p%20%7C%20H.265%20%7C%20WEB-DL/Episode%2004.mkv",
		"ep_05" : "https://kmdl.eu.org/0:/A%20Killer%20Paradox%20%7C%202024%20%7C%207.3%20%F0%9F%8C%90%F0%9F%94%9E/Multi%20Audio%20%7C%20Korean%20%7C%20English%20Dubbed%20%7C%20Hindi%20Dubbed%20%7C%20720p%20%7C%20H.265%20%7C%20WEB-DL/Episode%2005.mkv",
		"ep_06" : "https://kmdl.eu.org/0:/A%20Killer%20Paradox%20%7C%202024%20%7C%207.3%20%F0%9F%8C%90%F0%9F%94%9E/Multi%20Audio%20%7C%20Korean%20%7C%20English%20Dubbed%20%7C%20Hindi%20Dubbed%20%7C%20720p%20%7C%20H.265%20%7C%20WEB-DL/Episode%2006.mkv",
		"ep_07" : "https://kmdl.eu.org/0:/A%20Killer%20Paradox%20%7C%202024%20%7C%207.3%20%F0%9F%8C%90%F0%9F%94%9E/Multi%20Audio%20%7C%20Korean%20%7C%20English%20Dubbed%20%7C%20Hindi%20Dubbed%20%7C%20720p%20%7C%20H.265%20%7C%20WEB-DL/Episode%2007.mkv",
		"ep_08" : "https://kmdl.eu.org/0:/A%20Killer%20Paradox%20%7C%202024%20%7C%207.3%20%F0%9F%8C%90%F0%9F%94%9E/Multi%20Audio%20%7C%20Korean%20%7C%20English%20Dubbed%20%7C%20Hindi%20Dubbed%20%7C%20720p%20%7C%20H.265%20%7C%20WEB-DL/Episode%2008.mkv"
	},
	{
		"name" : "My Girlfriend Is a Gumiho",
		"language":"Bangla",
		"rating" : "7.6/10",
		"image_url" : "https://i.ibb.co/67Btkz7V/4e5414ee78fb4a6d66d6345b5ada159147de4285d8406304e5093e4c387da5d8.jpg",
		"ep_01" : "https://kmdl.eu.org/0:/My%20Girlfriend%20is%20a%20Gumiho%20%7C%202010%20%7C%207.7%20%F0%9F%8C%90/Bangla%20Dubbed%20%7C%20720p%20%7C%20H.264%20%7C%20WEB-DL/Episode%2001.mkv",
		"ep_02" : "https://kmdl.eu.org/0:/My%20Girlfriend%20is%20a%20Gumiho%20%7C%202010%20%7C%207.7%20%F0%9F%8C%90/Bangla%20Dubbed%20%7C%20720p%20%7C%20H.264%20%7C%20WEB-DL/Episode%2002.mkv",
		"ep_03" : "https://kmdl.eu.org/0:/My%20Girlfriend%20is%20a%20Gumiho%20%7C%202010%20%7C%207.7%20%F0%9F%8C%90/Bangla%20Dubbed%20%7C%20720p%20%7C%20H.264%20%7C%20WEB-DL/Episode%2003.mkv",
		"ep_04" : "https://kmdl.eu.org/0:/My%20Girlfriend%20is%20a%20Gumiho%20%7C%202010%20%7C%207.7%20%F0%9F%8C%90/Bangla%20Dubbed%20%7C%20720p%20%7C%20H.264%20%7C%20WEB-DL/Episode%2004.mkv",
		"ep_05" : "https://kmdl.eu.org/0:/My%20Girlfriend%20is%20a%20Gumiho%20%7C%202010%20%7C%207.7%20%F0%9F%8C%90/Bangla%20Dubbed%20%7C%20720p%20%7C%20H.264%20%7C%20WEB-DL/Episode%2005.mkv",
		"ep_06" : "https://kmdl.eu.org/0:/My%20Girlfriend%20is%20a%20Gumiho%20%7C%202010%20%7C%207.7%20%F0%9F%8C%90/Bangla%20Dubbed%20%7C%20720p%20%7C%20H.264%20%7C%20WEB-DL/Episode%2006.mkv",
		"ep_07" : "https://kmdl.eu.org/0:/My%20Girlfriend%20is%20a%20Gumiho%20%7C%202010%20%7C%207.7%20%F0%9F%8C%90/Bangla%20Dubbed%20%7C%20720p%20%7C%20H.264%20%7C%20WEB-DL/Episode%2007.mkv",
		"ep_08" : "https://kmdl.eu.org/0:/My%20Girlfriend%20is%20a%20Gumiho%20%7C%202010%20%7C%207.7%20%F0%9F%8C%90/Bangla%20Dubbed%20%7C%20720p%20%7C%20H.264%20%7C%20WEB-DL/Episode%2008.mkv",
		"ep_09" : "https://kmdl.eu.org/0:/My%20Girlfriend%20is%20a%20Gumiho%20%7C%202010%20%7C%207.7%20%F0%9F%8C%90/Bangla%20Dubbed%20%7C%20720p%20%7C%20H.264%20%7C%20WEB-DL/Episode%2009.mkv",
		"ep_10" : "https://kmdl.eu.org/0:/My%20Girlfriend%20is%20a%20Gumiho%20%7C%202010%20%7C%207.7%20%F0%9F%8C%90/Bangla%20Dubbed%20%7C%20720p%20%7C%20H.264%20%7C%20WEB-DL/Episode%2010.mkv",
		"ep_11" : "https://kmdl.eu.org/0:/My%20Girlfriend%20is%20a%20Gumiho%20%7C%202010%20%7C%207.7%20%F0%9F%8C%90/Bangla%20Dubbed%20%7C%20720p%20%7C%20H.264%20%7C%20WEB-DL/Episode%2011.mkv",
		"ep_12" : "https://kmdl.eu.org/0:/My%20Girlfriend%20is%20a%20Gumiho%20%7C%202010%20%7C%207.7%20%F0%9F%8C%90/Bangla%20Dubbed%20%7C%20720p%20%7C%20H.264%20%7C%20WEB-DL/Episode%2012.mkv",
		"ep_13" : "https://kmdl.eu.org/0:/My%20Girlfriend%20is%20a%20Gumiho%20%7C%202010%20%7C%207.7%20%F0%9F%8C%90/Bangla%20Dubbed%20%7C%20720p%20%7C%20H.264%20%7C%20WEB-DL/Episode%2013.mkv",
		"ep_14" : "https://kmdl.eu.org/0:/My%20Girlfriend%20is%20a%20Gumiho%20%7C%202010%20%7C%207.7%20%F0%9F%8C%90/Bangla%20Dubbed%20%7C%20720p%20%7C%20H.264%20%7C%20WEB-DL/Episode%2014.mkv",
		"ep_15" : "https://kmdl.eu.org/0:/My%20Girlfriend%20is%20a%20Gumiho%20%7C%202010%20%7C%207.7%20%F0%9F%8C%90/Bangla%20Dubbed%20%7C%20720p%20%7C%20H.264%20%7C%20WEB-DL/Episode%2015.mkv",
		"ep_16" : "https://kmdl.eu.org/0:/My%20Girlfriend%20is%20a%20Gumiho%20%7C%202010%20%7C%207.7%20%F0%9F%8C%90/Bangla%20Dubbed%20%7C%20720p%20%7C%20H.264%20%7C%20WEB-DL/Episode%2016.mkv"
	},
	{
		"name" : "Extraordinary Attorney Woo",
		"language":"Multi Audio Hindi / English",
		"rating" : "8.6/10",
		"image_url" : "https://i.ibb.co/8gwBLKPZ/p22283469-b-h8-ac.jpg",
		"ep_01" : "https://kmdl.eu.org/0:/Extraordinary%20Attorney%20Woo%20%7C%202022%20%7C%208.8%20%F0%9F%8C%90/Multi%20Audio%20%7C%20Korean%20%7C%20English%20Dubbed%20%7C%20Hindi%20Dubbed%20%7C%20720p%20%7C%20H.265%20%7C%20WEB-DL/Episode%2001.mkv",
		"ep_02" : "https://kmdl.eu.org/0:/Extraordinary%20Attorney%20Woo%20%7C%202022%20%7C%208.8%20%F0%9F%8C%90/Multi%20Audio%20%7C%20Korean%20%7C%20English%20Dubbed%20%7C%20Hindi%20Dubbed%20%7C%20720p%20%7C%20H.265%20%7C%20WEB-DL/Episode%2002.mkv",
		"ep_03" : "https://kmdl.eu.org/0:/Extraordinary%20Attorney%20Woo%20%7C%202022%20%7C%208.8%20%F0%9F%8C%90/Multi%20Audio%20%7C%20Korean%20%7C%20English%20Dubbed%20%7C%20Hindi%20Dubbed%20%7C%20720p%20%7C%20H.265%20%7C%20WEB-DL/Episode%2003.mkv",
		"ep_04" : "https://kmdl.eu.org/0:/Extraordinary%20Attorney%20Woo%20%7C%202022%20%7C%208.8%20%F0%9F%8C%90/Multi%20Audio%20%7C%20Korean%20%7C%20English%20Dubbed%20%7C%20Hindi%20Dubbed%20%7C%20720p%20%7C%20H.265%20%7C%20WEB-DL/Episode%2004.mkv",
		"ep_05" : "https://kmdl.eu.org/0:/Extraordinary%20Attorney%20Woo%20%7C%202022%20%7C%208.8%20%F0%9F%8C%90/Multi%20Audio%20%7C%20Korean%20%7C%20English%20Dubbed%20%7C%20Hindi%20Dubbed%20%7C%20720p%20%7C%20H.265%20%7C%20WEB-DL/Episode%2005.mkv",
		"ep_06" : "https://kmdl.eu.org/0:/Extraordinary%20Attorney%20Woo%20%7C%202022%20%7C%208.8%20%F0%9F%8C%90/Multi%20Audio%20%7C%20Korean%20%7C%20English%20Dubbed%20%7C%20Hindi%20Dubbed%20%7C%20720p%20%7C%20H.265%20%7C%20WEB-DL/Episode%2006.mkv",
		"ep_07" : "https://kmdl.eu.org/0:/Extraordinary%20Attorney%20Woo%20%7C%202022%20%7C%208.8%20%F0%9F%8C%90/Multi%20Audio%20%7C%20Korean%20%7C%20English%20Dubbed%20%7C%20Hindi%20Dubbed%20%7C%20720p%20%7C%20H.265%20%7C%20WEB-DL/Episode%2007.mkv",
		"ep_08" : "https://kmdl.eu.org/0:/Extraordinary%20Attorney%20Woo%20%7C%202022%20%7C%208.8%20%F0%9F%8C%90/Multi%20Audio%20%7C%20Korean%20%7C%20English%20Dubbed%20%7C%20Hindi%20Dubbed%20%7C%20720p%20%7C%20H.265%20%7C%20WEB-DL/Episode%2008.mkv",
		"ep_09" : "https://kmdl.eu.org/0:/Extraordinary%20Attorney%20Woo%20%7C%202022%20%7C%208.8%20%F0%9F%8C%90/Multi%20Audio%20%7C%20Korean%20%7C%20English%20Dubbed%20%7C%20Hindi%20Dubbed%20%7C%20720p%20%7C%20H.265%20%7C%20WEB-DL/Episode%2009.mkv",
		"ep_10" : "https://kmdl.eu.org/0:/Extraordinary%20Attorney%20Woo%20%7C%202022%20%7C%208.8%20%F0%9F%8C%90/Multi%20Audio%20%7C%20Korean%20%7C%20English%20Dubbed%20%7C%20Hindi%20Dubbed%20%7C%20720p%20%7C%20H.265%20%7C%20WEB-DL/Episode%2010.mkv",
		"ep_11" : "https://kmdl.eu.org/0:/Extraordinary%20Attorney%20Woo%20%7C%202022%20%7C%208.8%20%F0%9F%8C%90/Multi%20Audio%20%7C%20Korean%20%7C%20English%20Dubbed%20%7C%20Hindi%20Dubbed%20%7C%20720p%20%7C%20H.265%20%7C%20WEB-DL/Episode%2011.mkv",
		"ep_12" : "https://kmdl.eu.org/0:/Extraordinary%20Attorney%20Woo%20%7C%202022%20%7C%208.8%20%F0%9F%8C%90/Multi%20Audio%20%7C%20Korean%20%7C%20English%20Dubbed%20%7C%20Hindi%20Dubbed%20%7C%20720p%20%7C%20H.265%20%7C%20WEB-DL/Episode%2012.mkv",
		"ep_13" : "https://kmdl.eu.org/0:/Extraordinary%20Attorney%20Woo%20%7C%202022%20%7C%208.8%20%F0%9F%8C%90/Multi%20Audio%20%7C%20Korean%20%7C%20English%20Dubbed%20%7C%20Hindi%20Dubbed%20%7C%20720p%20%7C%20H.265%20%7C%20WEB-DL/Episode%2013.mkv",
		"ep_14" : "https://kmdl.eu.org/0:/Extraordinary%20Attorney%20Woo%20%7C%202022%20%7C%208.8%20%F0%9F%8C%90/Multi%20Audio%20%7C%20Korean%20%7C%20English%20Dubbed%20%7C%20Hindi%20Dubbed%20%7C%20720p%20%7C%20H.265%20%7C%20WEB-DL/Episode%2014.mkv",
		"ep_15" : "https://kmdl.eu.org/0:/Extraordinary%20Attorney%20Woo%20%7C%202022%20%7C%208.8%20%F0%9F%8C%90/Multi%20Audio%20%7C%20Korean%20%7C%20English%20Dubbed%20%7C%20Hindi%20Dubbed%20%7C%20720p%20%7C%20H.265%20%7C%20WEB-DL/Episode%2015.mkv",
		"ep_16" : "https://kmdl.eu.org/0:/Extraordinary%20Attorney%20Woo%20%7C%202022%20%7C%208.8%20%F0%9F%8C%90/Multi%20Audio%20%7C%20Korean%20%7C%20English%20Dubbed%20%7C%20Hindi%20Dubbed%20%7C%20720p%20%7C%20H.265%20%7C%20WEB-DL/Episode%2016.mkv"
	}
]
